hi_hahahellooo/__init__.py
hi_hahahellooo/hello.py
hi_hahahellooo-0.7.0.dist-info/METADATA
hi_hahahellooo-0.7.0.dist-info/WHEEL
hi_hahahellooo-0.7.0.dist-info/entry_points.txt
hi_hahahellooo-0.7.0.dist-info/top_level.txt
hi_hahahellooo-0.7.0.dist-info/RECORD
